prototypal-0.1.1.dist-info/METADATA
prototypal-0.1.1.dist-info/WHEEL
prototypal/__init__.py
prototypal/classy.py
prototypal/doc.py
prototypal/prototype.py
prototypal/py2/classy.py
prototypal/py2/demo.py
prototypal/py2/doc.py
prototypal/py2/prototype.py
prototypal-0.1.1.dist-info/RECORD
