Metadata-Version: 2.1
Name: prototypal
Version: 0.1.1
Summary: Javascript-like prototypes for Python.
Author-Email: bitnom <14287229+bitnom@users.noreply.github.com>
License: MIT
Project-URL: Repository, https://github.com/bitnom/prototypal
Requires-Python: >=3.11
